{
  "cli": {
    "version": ">= 7.0.0",
    "appVersionSource": "local"
  },
  "build": {
    "development": {
      "developmentClient": true,
      "distribution": "internal",
      "android": {
        "buildType": "apk",
        "gradleCommand": ":app:assembleDebug"
      },
      "env": {
        "EXPO_PUBLIC_API_URL": "http://192.168.1.100:3000/api",
        "EXPO_PUBLIC_SUPABASE_URL": "https://your-dev-project.supabase.co",
        "EXPO_PUBLIC_SUPABASE_ANON_KEY": "your-dev-anon-key"
      }
    },
    "preview": {
      "distribution": "internal",
      "android": {
        "buildType": "apk"
      },
      "env": {
        "EXPO_PUBLIC_API_URL": "https://api-staging.yourcourier.com/api",
        "EXPO_PUBLIC_SUPABASE_URL": "https://your-staging-project.supabase.co",
        "EXPO_PUBLIC_SUPABASE_ANON_KEY": "your-staging-anon-key"
      }
    },
    "production": {
      "autoIncrement": "version",
      "android": {
        "buildType": "app-bundle"
      },
      "ios": {
        "credentialsSource": "remote"
      },
      "env": {
        "EXPO_PUBLIC_API_URL": "https://api.yourcourier.com/api",
        "EXPO_PUBLIC_SUPABASE_URL": "https://your-prod-project.supabase.co",
        "EXPO_PUBLIC_SUPABASE_ANON_KEY": "your-prod-anon-key"
      }
    }
  },
  "submit": {
    "production": {
      "android": {
        "serviceAccountKeyPath": "./play-store-service-account.json",
        "track":                 "internal",
        "releaseStatus":         "draft",
        "changesNotSentForReview": false
      },
      "ios": {
        "ascAppId":     "YOUR_APP_STORE_CONNECT_APP_ID",
        "appleId":      "YOUR_APPLE_ID_EMAIL",
        "ascApiKeyPath": "./app-store-key.p8",
        "ascApiKeyId":   "YOUR_API_KEY_ID",
        "ascApiIssuerId": "YOUR_ISSUER_ID"
      }
    }
  }
}
